[
  {
    "id": "1733923640810",
    "username": "string",
    "password": "$2a$10$WlLhAUZVaxeX7P4SpRW8AO5M9lCX7g2Aur55sYOtDsXZpNC6zmZiy"
  },
  {
    "id": "1746335350798",
    "username": "mahdiyeh",
    "password": "$2a$10$7IG0m9RYQznH7GMCXHn7cuf7q1AWGzOXWoPG5C48K3vOBXcSl.i.K"
  },
  {
    "id": "1746341245434",
    "username": "mahdiyehabiyar",
    "password": "$2a$10$fuQvrTMYYl5fA/.C5icOn.J8m/5S70JbzmvhAassvLShXcroWxHyO"
  },
  {
    "id": "1746343944506",
    "username": "زیتطحسحمط",
    "password": "$2a$10$hCAb3HxnJy2nSVoB5RF0o.1npxG9U0zgU56AY4IRvuPGoemVt4Bsy"
  },
  {
    "id": "1746343973207",
    "username": "دبردیرد",
    "password": "$2a$10$yb2jSFY.wRfLIjiYh/luxOHqOo2vtpDaYJvl8zIHaHKWh2c07mcOe"
  },
  {
    "id": "1746345601280",
    "username": "سmahdiyeh",
    "password": "$2a$10$qNgIQMv5JqMMQP8lCkA6Uuzu2GNPkQ51XcIkOIyKdh3TTmKjTa3rO"
  }
]